{
  "key": "a649545c-8e00-46a0-b817-2d91fd22a162",
  "createdAt": "2025-10-24T21:14:43.126Z",
  "payload": {
    "kommission": "AT-",
    "datum": "24.10.2025",
    "empfaenger": "esp",
    "ansprechpartner": "Herr Holda",
    "mail": "einkauf@aluterr.de",
    "telefon": "+49 2041 7529132",
    "farbe": "Anthrazit (Tiger 29/80077) DB 703 Eisenglimmerglau",
    "positionen": [
      {
        "produktnummer": "ALU-ABDP",
        "anzahl": "1",
        "laenge": "1000",
        "einheit": "mm"
      },
      {
        "produktnummer": "ALU-ABSCHL",
        "anzahl": "1",
        "laenge": "1000",
        "einheit": "mm"
      }
    ]
  }
}